slimformers/__init__.py
slimformers/cli.py
slimformers/discovery.py
slimformers/lora.py
slimformers/pruner.py
slimformers/py.typed
slimformers-1.12.0.dist-info/licenses/LICENSE.txt
slimformers-1.12.0.dist-info/METADATA
slimformers-1.12.0.dist-info/WHEEL
slimformers-1.12.0.dist-info/entry_points.txt
slimformers-1.12.0.dist-info/top_level.txt
slimformers-1.12.0.dist-info/RECORD
